proyecto/ejemplos/Seven_seg/src/design/top.sv
module top (
    input logic [3:0] sw,           // A (MSB), B,C,D.. Del 0 al 3 hay 4 bits
    output logic [6:0] segments,
    output logic [3:0] led  
);

    /* Esta seccion de codigo no representa nada funcional, solo se asigna un nombre a 
    cada bit para escribir las ecuaciones boooleanas con mayor facilidad.
    Como renombrar un nodo.     */
assign A = sw[3];
assign B = sw[2];
assign C = sw[1];
assign D = sw[0];
    //

    /*Esta seccion de codigo presenta la logica booleana necesaria para las salidas del sistema, 
    las cuales se deben conectar a un respectivo segmento del display.*/
    //Leds que representan los inputs (bits binarios) de los switches en la protoboard
assign led [0] = ~D;
assign led [1] = ~C;
assign led [2] = ~B;
assign led [3] = ~A;
//Toda la lógica booleana se obtuvo con un analísis de mapas de Karnaugh montado en Excel.
assign segments[0] = (~B & ~D) |               // segmento A
                    (~A & C) |
                    (A & ~D) |
                    (B & C) |
                    (A & ~B & ~C) |
                    (~A & B & D);  

assign segments[1] = (~B & ~C) |     // segmento B
                    (~B & ~D) |
                    (~A & ~C & ~D) |
                    (~A & C & D) |
                    (A & ~C & D); 

assign segments[2] = (~B & ~C) |     // segmento C
                    (~B & D) |
                    (~C & D) |
                    (~A & B ) |
                    (A & ~B);
        

assign segments[3] = (~B & ~C & ~D) |     // segmento D
                    (~A & C & ~D) |
                    (~B & C & D) |
                    (B & ~C & D) |
                    (A & B & ~D);

assign segments[4] = (~B & ~D) |          // segmento E
                    (C & ~D) |
                    (A & C)|
                    (A & B);

assign segments[5] = (~C & ~D) |         // segmento F
                    (B & ~D) |
                    (A & ~B) |
                    (A & C) |
                    (~A & B & ~C); 

assign segments[6] = (~B & C) |         // segmento G
                    (C & ~D) |
                    (A & ~B) |
                    (A & D) |
                    (~A & B & ~C);                            
    
endmodule

proyecto/ejemplos/Seven_seg/src/sim/top_tb.sv
`timescale 1ns/1ps

module top_tb;
    /*
    Observe que en esta seccion los logic no se definen como input o output, son propios del modulo
    como si fueran un nodo, por eso se conectan en el DUT. 
    */
    logic [3:0] sw;                         
    logic Sa, Sb, Sc, Sd, Se, Sf, Sg;
    logic [6:0] out;

    // DUT (Device Under Test)

    /*
    Observe que .sw se refiere al nodo sw creado en este propio modulo, (sw) se refiere al input 
    definido en el top. Se recomienda usar los mismos nombres porque esto permite seguir trabajando
    con el mismo nombre de variable y la conexion es mas facil. De igual forma para las demas.

    Observe que se prefiere usar los S# porque es mas facil y corto que escribir segments[#]...
    */
    top dut (
        .sw(sw),
        .segments({Sg,Sf,Se,Sd,Sc,Sb,Sa})
    );

    // Función que devuelve patrón esperado. Se utilizara para comparar 'segments' contra 'expected'
    function automatic [6:0] expected (input [3:0] val);
        case (val)
            4'd0: expected = 7'b0111111;
            4'd1: expected = 7'b0000110;
            4'd2: expected = 7'b1011011;
            4'd3: expected = 7'b1001111;
            4'd4: expected = 7'b1100110;
            4'd5: expected = 7'b1101101;
            4'd6: expected = 7'b1111101;
            4'd7: expected = 7'b0000111;
            4'd8: expected = 7'b1111111;
            4'd9: expected = 7'b1100111;
            4'd10: expected = 7'b1110111;
            4'd11: expected = 7'b1111100;
            4'd12: expected = 7'b0111001;
            4'd13: expected = 7'b1011110;
            4'd14: expected = 7'b1111001;
            // 15
            default: expected = 7'b1110001;
        endcase
    endfunction

    initial begin
        $display("Starting exhaustive test...");

        for (int i = 0; i < 16; i++) begin
            sw = i;
            #1;
            out = {Sg,Sf,Se,Sd,Sc,Sb,Sa};       

            if (out != expected(i)) begin
                $display("ERROR at %0d -> got %b expected %b",
                         i, out, expected(i));
            end
            else begin
                $display("OK %0d -> %b", i, out);
            end
        end

        $display("Test finished");
        $finish;
    end

    initial begin
        $dumpfile("top_tb.vcd");
        $dumpvars(0,top_tb);
    end

endmodule

proyecto/ejemplos/Seven_seg/src/build/top_tb.vcd
$date
	Tue Apr 14 21:08:49 2026
$end
$version
	Icarus Verilog
$end
$timescale
	1ps
$end
$scope module top_tb $end
$var wire 1 ! Sg $end
$var wire 1 " Sf $end
$var wire 1 # Se $end
$var wire 1 $ Sd $end
$var wire 1 % Sc $end
$var wire 1 & Sb $end
$var wire 1 ' Sa $end
$var reg 7 ( out [6:0] $end
$var reg 4 ) sw [3:0] $end
$scope function expected $end
$upscope $end
$scope module dut $end
$var wire 4 * sw [3:0] $end
$var wire 7 + segments [6:0] $end
$var wire 4 , led [3:0] $end
$var wire 1 - D $end
$var wire 1 . C $end
$var wire 1 / B $end
$var wire 1 0 A $end
$upscope $end
$scope begin $ivl_for_loop0 $end
$var integer 32 1 i [31:0] $end
$upscope $end
$upscope $end
$enddefinitions $end
$comment Show the parameter values. $end
$dumpall
$end
#0
$dumpvars
b0 1
00
0/
0.
0-
b1111 ,
b111111 +
b0 *
b0 )
bx (
1'
1&
1%
1$
1#
1"
0!
$end
#1000
0'
0"
0$
0#
b110 +
b1110 ,
1-
b1 )
b1 *
b1 1
b111111 (
#2000
0%
1'
1$
1!
1#
b1011011 +
b1101 ,
1.
0-
b10 )
b10 *
b10 1
b110 (
#3000
0#
1%
b1001111 +
b1100 ,
1-
b11 )
b11 *
b11 1
b1011011 (
#4000
0'
0$
1"
1&
b1100110 +
b1011 ,
1/
0.
0-
b100 )
b100 *
b100 1
b1001111 (
#5000
0&
1$
1'
b1101101 +
b1010 ,
1-
b101 )
b101 *
b101 1
b1100110 (
#6000
0&
1#
1!
1"
1$
1'
b1111101 +
b1001 ,
1.
0-
b110 )
b110 *
b110 1
b1101101 (
#7000
0!
0"
0$
0#
1&
b111 +
b1000 ,
1-
b111 )
b111 *
b111 1
b1111101 (
#8000
1$
1#
1!
1"
1&
b1111111 +
b111 ,
10
0/
0.
0-
b1000 )
b1000 *
b1000 1
b111 (
#9000
0$
0#
b1100111 +
b110 ,
1-
b1001 )
b1001 *
b1001 1
b1111111 (
#10000
0$
1'
1#
b1110111 +
b101 ,
1.
0-
b1010 )
b1010 *
b1010 1
b1100111 (
#11000
0&
0'
1$
b1111100 +
b100 ,
1-
b1011 )
b1011 *
b1011 1
b1110111 (
#12000
0!
0%
1'
b111001 +
b11 ,
1/
0.
0-
b1100 )
b1100 *
b1100 1
b1111100 (
#13000
0"
0'
1%
1!
1&
b1011110 +
b10 ,
1-
b1101 )
b1101 *
b1101 1
b111001 (
#14000
1'
0%
1"
1!
0&
b1111001 +
b1 ,
1.
0-
b1110 )
b1110 *
b1110 1
b1011110 (
#15000
0$
b1110001 +
b0 ,
1-
b1111 )
b1111 *
b1111 1
b1111001 (
#16000
b10000 1
b1110001 (
